MANIFEST.in
README.rst
setup.py
docs/HISTORY.txt
docs/LICENSE.GPL
docs/LICENSE.txt
ftw/__init__.py
ftw.contentnav.egg-info/PKG-INFO
ftw.contentnav.egg-info/SOURCES.txt
ftw.contentnav.egg-info/dependency_links.txt
ftw.contentnav.egg-info/entry_points.txt
ftw.contentnav.egg-info/namespace_packages.txt
ftw.contentnav.egg-info/not-zip-safe
ftw.contentnav.egg-info/requires.txt
ftw.contentnav.egg-info/top_level.txt
ftw/contentnav/__init__.py
ftw/contentnav/config.py
ftw/contentnav/configure.zcml
ftw/contentnav/hooks.py
ftw/contentnav/indexer.py
ftw/contentnav/interfaces.py
ftw/contentnav/lawgiver.zcml
ftw/contentnav/permissions.zcml
ftw/contentnav/testing.py
ftw/contentnav/vocabularies.py
ftw/contentnav/behaviors/__init__.py
ftw/contentnav/behaviors/configure.zcml
ftw/contentnav/behaviors/content_categories.py
ftw/contentnav/locales/ftw.contentnav.pot
ftw/contentnav/locales/de/LC_MESSAGES/ftw.contentnav.po
ftw/contentnav/profiles/default/metadata.xml
ftw/contentnav/profiles/default/rolemap.xml
ftw/contentnav/profiles/default/viewlets.xml
ftw/contentnav/tests/__init__.py
ftw/contentnav/tests/test_behavior.py
ftw/contentnav/tests/test_setup.py
ftw/contentnav/tests/test_viewlet.py
ftw/contentnav/tests/tests.zcml
ftw/contentnav/upgrades/__init__.py
ftw/contentnav/upgrades/20160808145033_render_content_nav_in_different_viewlet/__init__.py
ftw/contentnav/upgrades/20160808145033_render_content_nav_in_different_viewlet/upgrade.py
ftw/contentnav/upgrades/20160808145033_render_content_nav_in_different_viewlet/viewlets.xml
ftw/contentnav/viewlets/__init__.py
ftw/contentnav/viewlets/configure.zcml
ftw/contentnav/viewlets/contentnavlisting.pt
ftw/contentnav/viewlets/contentnavlisting.py